{
  "alfredtheme" : {
    "result" : {
      "textSpacing" : 4,
      "subtext" : {
        "size" : 11,
        "colorSelected" : "#6D6D6DFF",
        "font" : "Helvetica Neue Light",
        "color" : "#999999FF"
      },
      "shortcut" : {
        "size" : 16,
        "colorSelected" : "#A5A5A5FF",
        "font" : "Helvetica Neue Light",
        "color" : "#B2B2B2FF"
      },
      "backgroundSelected" : "#0000000F",
      "text" : {
        "size" : 16,
        "colorSelected" : "#000000FF",
        "font" : "Helvetica Neue Light",
        "color" : "#353535FF"
      },
      "iconPaddingHorizontal" : 5,
      "paddingVertical" : 4,
      "iconSize" : 40
    },
    "separator" : {
      "color" : "#00000000",
      "thickness" : 1
    },
    "search" : {
      "paddingVertical" : 2,
      "background" : "#00000000",
      "spacing" : 10,
      "text" : {
        "size" : 32,
        "colorSelected" : "#000000FF",
        "font" : "Helvetica Neue Light",
        "color" : "#000000FF"
      },
      "backgroundSelected" : "#B2D7FFFF"
    },
    "scrollbar" : {
      "color" : "#00000019",
      "thickness" : 2
    },
    "name" : "Wide Yosemite (v2)",
    "window" : {
      "color" : "#FFFFFFF9",
      "paddingHorizontal" : 10,
      "width" : 680,
      "borderPadding" : 10,
      "borderColor" : "#00000000",
      "blur" : 0,
      "roundness" : 3,
      "paddingVertical" : 10
    }
  }
}